{
  "cars": [
    {
      "img":"http://www.thetorquereport.com/assets_c/2011/07/2011_Honda_Accord_EX_L_V6_Sedan-thumb-530x353-13277.jpg",
      "make": "Honda",
      "model": "Accord",
      "year": 2005,
      "price": 10888,
      "color": "DimGrey",
      "purchased": true,
      "description": "This is an immaculate 2006 Nissan Rogue with only 25000 miles on it. Leather seats, power everything."
    },
    {
      "img":"http://images.autosofasia.com/pictures/49233943.jpg",
      "make": "Toyota",
      "model": "Corolla",
      "year": 2004,
      "price": 8999,
      "color": "FloralWhite",
      "purchased": false,
      "description": "This is an immaculate 2006 Nissan Rogue with only 25000 miles on it. Leather seats, power everything."
    },
    {
      "img":"http://www.classycars.org/Toyota/Toyota.2011.Sienna.xle.373.jpg",
      "make": "Toyota",
      "model": "Sienna",
      "year": 2001,
      "price": 10999,
      "color": "Gainsboro",
      "purchased": true,
      "description": "This is an immaculate 2006 Nissan Rogue with only 25000 miles on it. Leather seats, power everything."
    }
  ]
}
